odoo/addons/business_requirement_deliverable/README.rst
odoo/addons/business_requirement_deliverable/__init__.py
odoo/addons/business_requirement_deliverable/__manifest__.py
odoo/addons/business_requirement_deliverable/controllers/__init__.py
odoo/addons/business_requirement_deliverable/controllers/portal.py
odoo/addons/business_requirement_deliverable/data/business_data.xml
odoo/addons/business_requirement_deliverable/data/business_requirement_deliverable_demo.xml
odoo/addons/business_requirement_deliverable/i18n/business_requirement_deliverable.pot
odoo/addons/business_requirement_deliverable/i18n/es.po
odoo/addons/business_requirement_deliverable/i18n/fr.po
odoo/addons/business_requirement_deliverable/i18n/sl.po
odoo/addons/business_requirement_deliverable/models/__init__.py
odoo/addons/business_requirement_deliverable/models/brd_section.py
odoo/addons/business_requirement_deliverable/models/business.py
odoo/addons/business_requirement_deliverable/models/res_partner.py
odoo/addons/business_requirement_deliverable/readme/CONFIGURE.rst
odoo/addons/business_requirement_deliverable/readme/CONTRIBUTORS.rst
odoo/addons/business_requirement_deliverable/readme/DESCRIPTION.rst
odoo/addons/business_requirement_deliverable/readme/USAGE.rst
odoo/addons/business_requirement_deliverable/security/business_requirement_deliverable_security.xml
odoo/addons/business_requirement_deliverable/security/ir.model.access.csv
odoo/addons/business_requirement_deliverable/static/description/icon.png
odoo/addons/business_requirement_deliverable/static/description/index.html
odoo/addons/business_requirement_deliverable/static/img/bus_req_deliverable.png
odoo/addons/business_requirement_deliverable/static/img/bus_req_deliverable2.png
odoo/addons/business_requirement_deliverable/static/img/bus_req_report1.png
odoo/addons/business_requirement_deliverable/static/img/bus_req_report2.png
odoo/addons/business_requirement_deliverable/static/img/bus_req_report3.png
odoo11_addon_business_requirement_deliverable-11.0.1.3.1.dist-info/METADATA
odoo11_addon_business_requirement_deliverable-11.0.1.3.1.dist-info/WHEEL
odoo11_addon_business_requirement_deliverable-11.0.1.3.1.dist-info/top_level.txt
odoo11_addon_business_requirement_deliverable-11.0.1.3.1.dist-info/RECORD
